GreenPonik_Thermistor10k/Thermistor10k.py
GreenPonik_Thermistor10k/__init__.py
tests/__init__.py
tests/test_Thermistor10k.py
greenponik_thermistor10k-0.0.16.dist-info/METADATA
greenponik_thermistor10k-0.0.16.dist-info/WHEEL
greenponik_thermistor10k-0.0.16.dist-info/top_level.txt
greenponik_thermistor10k-0.0.16.dist-info/RECORD
