Metadata-Version: 2.1
Name: greenponik-thermistor10k
Version: 0.0.16
Summary: Read temperature on thermistor 10k through Python3 on raspberry pi
Home-page: https://github.com/GreenPonik/GreenPonik_Thermistor10k
Author: GreenPonik SAS
Author-email: contact@greenponik.com
License: MIT
Project-URL: Source, https://github.com/GreenPonik/GreenPonik_Thermistor10k/
Project-URL: Bug Reports, https://github.com/GreenPonik/GreenPonik_Thermistor10k/issues
Keywords: GreenPonik hydroponics thermistor 10k ohm          temperature reader python hardware diy iot raspberry pi
Platform: UNKNOWN
Classifier: Programming Language :: Python :: 3
Classifier: License :: OSI Approved :: MIT License
Classifier: Operating System :: OS Independent
Requires-Python: >=3.6.0
Requires-Dist: adafruit-blinka
Requires-Dist: adafruit-circuitpython-ads1x15
Requires-Dist: adafruit-extended-bus
